{
  "operations": [
    {
      "id": "wix-rest-universal.query-sites",
      "method": "POST",
      "urlTemplate": "https://www.wixapis.com/site-list/v2/sites/query",
      "authModes": ["oauth", "api_key"],
      "requiredParams": [],
      "bodyRequired": false,
      "sourceDocUrl": "https://dev.wix.com/docs/api-reference/account-level/sites/sites/query-sites"
    },
    {
      "id": "wix-rest-universal.query-contacts",
      "method": "POST",
      "urlTemplate": "https://www.wixapis.com/contacts/v4/contacts/query",
      "authModes": ["signed_instance", "oauth", "api_key"],
      "requiredParams": [],
      "bodyRequired": false,
      "sourceDocUrl": "https://dev.wix.com/docs/api-reference/crm/members-contacts/contacts/contacts/contact-v4/query-contacts"
    },
    {
      "id": "wix-rest-universal.list-files",
      "method": "GET",
      "urlTemplate": "https://www.wixapis.com/site-media/v1/files",
      "authModes": ["signed_instance", "oauth", "api_key"],
      "requiredParams": [],
      "bodyRequired": false,
      "sourceDocUrl": "https://dev.wix.com/docs/api-reference/assets/media/media-manager/files/list-files"
    }
  ]
}
